sc_sme_diff_analysis/__init__.py
sc_sme_diff_analysis/main.py
sc_sme_diff_analysis/utils.py
sc_sme_diff_analysis/analyzer/__init__.py
sc_sme_diff_analysis/analyzer/branch_summary_diff_analyzer.py
sc_sme_diff_analysis/analyzer/diff_analyzer.py
sc_sme_diff_analysis/analyzer/manager_summary_diff_analyzer.py
sc_sme_diff_analysis/analyzer/valid_clearing_account_detail_diff_analyzer.py
sc_sme_diff_analysis/analyzer/valid_credit_account_detail_diff_analyzer.py
sc_sme_diff_analysis/configs/__init__.py
sc_sme_diff_analysis/configs/default.py
sc_sme_diff_analysis/tests/__init__.py
sc_sme_diff_analysis/tests/sample_config/production.yml
sc_sme_diff_analysis-0.0.5.dist-info/LICENSE
sc_sme_diff_analysis-0.0.5.dist-info/METADATA
sc_sme_diff_analysis-0.0.5.dist-info/WHEEL
sc_sme_diff_analysis-0.0.5.dist-info/entry_points.txt
sc_sme_diff_analysis-0.0.5.dist-info/top_level.txt
sc_sme_diff_analysis-0.0.5.dist-info/RECORD
