Metadata-Version: 2.1
Name: sc-sme-diff-analysis
Version: 0.0.5
Summary: SME diff analysis
Home-page: https://github.com/Scott-Lau/sc-sme-diff-analysis
Author: Scott Lau
Author-email: exceedego@126.com
License: MIT
Keywords: python SME diff analysis
Platform: POSIX
Classifier: Programming Language :: Python :: 3
Classifier: Programming Language :: Python :: 3.6
Classifier: Programming Language :: Python :: 3.7
Classifier: Programming Language :: Python :: 3.8
Classifier: Programming Language :: Python :: 3.9
Classifier: License :: OSI Approved :: MIT License
Classifier: Operating System :: OS Independent
Classifier: Topic :: Software Development
Classifier: Topic :: Utilities
Requires-Python: >=3.6
License-File: LICENSE
Requires-Dist: sc-utilities (>=0.0.6)
Requires-Dist: sc-config (>=0.0.8)
Requires-Dist: sc-analyzer-base (>=0.0.3)
Requires-Dist: pandas (>=1.3.2)
Requires-Dist: openpyxl (>=3.0.7)
